unittest_sheraf/__init__.py
unittest_sheraf/utils.py
unittest_sheraf-0.1.0.dist-info/METADATA
unittest_sheraf-0.1.0.dist-info/WHEEL
unittest_sheraf-0.1.0.dist-info/top_level.txt
unittest_sheraf-0.1.0.dist-info/RECORD
