Metadata-Version: 2.1
Name: unittest-sheraf
Version: 0.1.0
Summary: Versatile ZODB abstraction layer - unittest fixtures
Home-page: https://gitlab.com/yaal/unittest-sheraf
Author: Yaal team
Author-email: contact@yaal.fr
License: MIT
Keywords: zodb,orm,test,unittest
Platform: UNKNOWN
Classifier: Intended Audience :: Developers
Classifier: Programming Language :: Python :: 3.5
Classifier: Programming Language :: Python :: 3.6
Classifier: Programming Language :: Python :: 3.7
Classifier: Programming Language :: Python :: 3.8
Classifier: Programming Language :: Python :: Implementation :: CPython
Classifier: License :: OSI Approved :: MIT License
Classifier: Topic :: Software Development :: Libraries :: Python Modules
Classifier: Framework :: ZODB
Classifier: Framework :: Pytest
Requires-Dist: portpicker
